Changelog.md
LICENSE
MANIFEST.in
README.md
pyproject.toml
requirements.txt
setup.cfg
setup.py
supportedsites.md
devscripts/SizeOfImage.patch
devscripts/SizeOfImage_w.patch
devscripts/__init__.py
devscripts/bash-completion.in
devscripts/bash-completion.py
devscripts/changelog_override.json
devscripts/changelog_override.schema.json
devscripts/check-porn.py
devscripts/cli_to_api.py
devscripts/fish-completion.in
devscripts/fish-completion.py
devscripts/generate_aes_testdata.py
devscripts/lazy_load_template.py
devscripts/logo.ico
devscripts/make_changelog.py
devscripts/make_contributing.py
devscripts/make_issue_template.py
devscripts/make_lazy_extractors.py
devscripts/make_readme.py
devscripts/make_supportedsites.py
devscripts/prepare_manpage.py
devscripts/run_tests.bat
devscripts/run_tests.sh
devscripts/set-variant.py
devscripts/update-formulae.py
devscripts/update-version.py
devscripts/utils.py
devscripts/zsh-completion.in
devscripts/zsh-completion.py
devscripts/__pycache__/__init__.cpython-310.pyc
devscripts/__pycache__/utils.cpython-310.pyc
pragy_dl/YoutubeDL.py
pragy_dl/__init__.py
pragy_dl/__main__.py
pragy_dl/aes.py
pragy_dl/cache.py
pragy_dl/casefold.py
pragy_dl/cookies.py
pragy_dl/jsinterp.py
pragy_dl/minicurses.py
pragy_dl/options.py
pragy_dl/plugins.py
pragy_dl/socks.py
pragy_dl/update.py
pragy_dl/version.py
pragy_dl/webvtt.py
pragy_dl.egg-info/PKG-INFO
pragy_dl.egg-info/SOURCES.txt
pragy_dl.egg-info/dependency_links.txt
pragy_dl.egg-info/entry_points.txt
pragy_dl.egg-info/requires.txt
pragy_dl.egg-info/top_level.txt
pragy_dl/__pyinstaller/__init__.py
pragy_dl/__pyinstaller/hook-yt_dlp.py
pragy_dl/compat/__init__.py
pragy_dl/compat/_deprecated.py
pragy_dl/compat/_legacy.py
pragy_dl/compat/compat_utils.py
pragy_dl/compat/functools.py
pragy_dl/compat/imghdr.py
pragy_dl/compat/shutil.py
pragy_dl/compat/types.py
pragy_dl/compat/urllib/__init__.py
pragy_dl/compat/urllib/request.py
pragy_dl/dependencies/Cryptodome.py
pragy_dl/dependencies/__init__.py
pragy_dl/downloader/__init__.py
pragy_dl/downloader/common.py
pragy_dl/downloader/dash.py
pragy_dl/downloader/external.py
pragy_dl/downloader/f4m.py
pragy_dl/downloader/fc2.py
pragy_dl/downloader/fragment.py
