Metadata-Version: 2.1
Name: pragy-dl
Version: 2023.10.7
Summary: A youtube-dl fork with additional features and patches
Home-page: https://github.com/pragy-dl/pragy-dl
Maintainer: pukkandan
Maintainer-email: pukkandan.ytdlp@gmail.com
Project-URL: Documentation, https://github.com/pragy-dl/pragy-dl#readme
Project-URL: Source, https://github.com/pragy-dl/pragy-dl
Project-URL: Tracker, https://github.com/pragy-dl/pragy-dl/issues
Project-URL: Funding, https://github.com/pragy-dl/pragy-dl/blob/master/Collaborators.md#collaborators
Classifier: Topic :: Multimedia :: Video
Classifier: Development Status :: 5 - Production/Stable
Classifier: Environment :: Console
Classifier: Programming Language :: Python
Classifier: Programming Language :: Python :: 3.7
Classifier: Programming Language :: Python :: 3.8
Classifier: Programming Language :: Python :: 3.9
Classifier: Programming Language :: Python :: 3.10
Classifier: Programming Language :: Python :: 3.11
Classifier: Programming Language :: Python :: Implementation
Classifier: Programming Language :: Python :: Implementation :: CPython
Classifier: Programming Language :: Python :: Implementation :: PyPy
Classifier: License :: Public Domain
Classifier: Operating System :: OS Independent
Requires-Python: >=3.7
License-File: LICENSE
Requires-Dist: mutagen
Requires-Dist: pycryptodomex
Requires-Dist: websockets
Requires-Dist: brotli; platform_python_implementation == "CPython"
Requires-Dist: brotlicffi; platform_python_implementation != "CPython"
Requires-Dist: certifi
